multimodal_sdk/__init__.py
multimodal_sdk/common/__init__.py
multimodal_sdk/common/base.py
multimodal_sdk/common/decorators.py
multimodal_sdk/common/http_status_handler.py
multimodal_sdk/common/rate_limiter.py
multimodal_sdk/common/refresh.py
multimodal_sdk/common/retry_decorator.py
multimodal_sdk/knowledge_base/__init__.py
multimodal_sdk/knowledge_base/abstract_class.py
multimodal_sdk/knowledge_base/controller.py
multimodal_sdk/knowledge_base/main.py
multimodal_sdk/knowledge_base/poll_task_status.py
multimodal_sdk/role/__init__.py
multimodal_sdk/role/abstract_class.py
multimodal_sdk/role/controller.py
multimodal_sdk/role/main.py
multimodal_sdk/tenant/__init__.py
multimodal_sdk/tenant/abstract_class.py
multimodal_sdk/tenant/controller.py
multimodal_sdk/tenant/main.py
multimodal_sdk/user_handler/__init__.py
multimodal_sdk/user_handler/abstract_class.py
multimodal_sdk/user_handler/controller.py
multimodal_sdk/user_handler/main.py
multimodal_sdk-0.0.6.67.30.dist-info/METADATA
multimodal_sdk-0.0.6.67.30.dist-info/WHEEL
multimodal_sdk-0.0.6.67.30.dist-info/top_level.txt
multimodal_sdk-0.0.6.67.30.dist-info/RECORD
