Metadata-Version: 2.4
Name: multimodal_sdk
Version: 0.0.6.67.30
Requires-Dist: aiofiles==23.2.1
Requires-Dist: aiohttp==3.9.5
Requires-Dist: aiosignal==1.3.1
Requires-Dist: attrs==23.2.0
Requires-Dist: certifi==2024.6.2
Requires-Dist: charset-normalizer==3.3.2
Requires-Dist: colorama==0.4.6
Requires-Dist: frozenlist==1.4.1
Requires-Dist: idna==3.7
Requires-Dist: iniconfig==2.0.0
Requires-Dist: multidict==6.0.5
Requires-Dist: packaging==24.1
Requires-Dist: pluggy==1.5.0
Requires-Dist: pytest==8.2.2
Requires-Dist: pytest-asyncio==0.23.7
Requires-Dist: pytest-order==1.2.1
Requires-Dist: python-dotenv==1.0.1
Requires-Dist: requests==2.32.3
Requires-Dist: urllib3==2.2.1
Requires-Dist: yarl==1.9.4
Requires-Dist: tenacity
Requires-Dist: aiolimiter
Dynamic: requires-dist
